gempaterkini/__init__.py
latestarthquake_indonesia-0.1.1.dist-info/LICENSE
latestarthquake_indonesia-0.1.1.dist-info/METADATA
latestarthquake_indonesia-0.1.1.dist-info/WHEEL
latestarthquake_indonesia-0.1.1.dist-info/top_level.txt
latestarthquake_indonesia-0.1.1.dist-info/RECORD
