Metadata-Version: 2.1
Name: latestarthquake-indonesia
Version: 0.1.1
Summary: This package will give us information about the latest earthquake in Indonesia. The data taken from BMKG (Meteorology, Climatology, and Geophysics Agency).
Home-page: https://github.com/wearenotrobot/latest-indonesian-earthquake
Author: mizan toyyibun
Author-email: untirta.mizan62@gmail.com
License: UNKNOWN
Project-URL: Github, https://github.com/wearenotrobot/latest-indonesian-earthquake
Platform: UNKNOWN
Classifier: Programming Language :: Python :: 3
Classifier: License :: OSI Approved :: GNU Lesser General Public License v3 (LGPLv3)
Classifier: Operating System :: OS Independent
Classifier: Development Status :: 3 - Alpha
Requires-Python: >=3.6
License-File: LICENSE
